csc_cyb600_jmdv/__init__.py
csc_cyb600_jmdv/main.py
csc_cyb600_nobin-1.0.2.data/scripts/say-hello-cyb600
csc_cyb600_nobin-1.0.2.dist-info/LICENSE
csc_cyb600_nobin-1.0.2.dist-info/METADATA
csc_cyb600_nobin-1.0.2.dist-info/WHEEL
csc_cyb600_nobin-1.0.2.dist-info/top_level.txt
csc_cyb600_nobin-1.0.2.dist-info/RECORD
