Metadata-Version: 2.1
Name: csc-cyb600-nobin
Version: 1.0.2
Summary: UNKNOWN
Home-page: UNKNOWN
Author: Nobin Jaison Johnson
Author-email: johns451@canisius.edu
License: Apache License Version 2.0
Platform: UNKNOWN
License-File: LICENSE
Requires-Dist: colorama
